star/__init__.py
star/_code_generator.py
star/_data_converter.py
star/alpha.py
star/alpha_materials.py
star/electron.py
star/proton.py
star/proton_materials.py
star/data/NIST_STAR.hdf5
xcom/__init__.py
xcom/_data_converter.py
xcom/interpolators.py
xcom/xcom.py
xcom/data/NIST_XCOM.hdf5
nist_calculators-0.0.5.dist-info/LICENSE
nist_calculators-0.0.5.dist-info/METADATA
nist_calculators-0.0.5.dist-info/WHEEL
nist_calculators-0.0.5.dist-info/top_level.txt
nist_calculators-0.0.5.dist-info/RECORD
