Metadata-Version: 2.1
Name: nist-calculators
Version: 0.0.5
Summary: Python implementaion of several NIST calculator
Home-page: http://npm.mipt.ru/
Author: Mikhail Zelenyi
Author-email: mihail.zelenyy@phystech.edu
License: MIT License
Project-URL: Bug Tracker, https://github.com/Zelenyy/nist-calculators/issues
Project-URL: Documentation, https://github.com/Zelenyy/nist-calculators
Project-URL: Source Code, https://github.com/Zelenyy/nist-calculators
Keywords: gamma-ray,cross-section,xcom
Platform: UNKNOWN
Classifier: Programming Language :: Python :: 3
Classifier: License :: OSI Approved :: MIT License
Classifier: Operating System :: OS Independent
Requires-Dist: numpy (>=1.8.2)
Requires-Dist: scipy (>=1.3.1)
Requires-Dist: tables (>=3.5.1)
